gfa_logging/__init__.py
gfa_logging/core.py
gfa_logging/custom_file_handler.py
gfa_logging-1.0.dist-info/LICENSE
gfa_logging-1.0.dist-info/METADATA
gfa_logging-1.0.dist-info/WHEEL
gfa_logging-1.0.dist-info/top_level.txt
gfa_logging-1.0.dist-info/RECORD
