Metadata-Version: 2.1
Name: gfa-logging
Version: 1.0
Summary: This library provide a logging class to record data or debug your application
Home-page: http://github.com/UMONS-GFA/gfa_logging
Author: Christophe Bastin
Author-email: UNKNOWN
License: GPL3
Platform: UNKNOWN
Classifier: Programming Language :: Python
Classifier: Development Status :: 1 - Planning
